xml2db/__init__.py
xml2db/document.py
xml2db/exceptions.py
xml2db/model.py
xml2db/xml_converter.py
xml2db/table/__init__.py
xml2db/table/column.py
xml2db/table/duplicated_table.py
xml2db/table/relations.py
xml2db/table/reused_table.py
xml2db/table/table.py
xml2db/table/transformed_table.py
xml2db-0.12.5.dist-info/licenses/LICENSE
xml2db-0.12.5.dist-info/METADATA
xml2db-0.12.5.dist-info/WHEEL
xml2db-0.12.5.dist-info/top_level.txt
xml2db-0.12.5.dist-info/RECORD
