Metadata-Version: 2.4
Name: xml2db
Version: 0.12.5
Summary: Import complex XML files to a relational database
Author-email: Commission de régulation de l'énergie <opensource@cre.fr>
Project-URL: Documentation, https://cre-dev.github.io/xml2db
Project-URL: Repository, https://github.com/cre-dev/xml2db
Project-URL: Issues page, https://github.com/cre-dev/xml2db/issues
Classifier: Programming Language :: Python :: 3
Classifier: License :: OSI Approved :: MIT License
Classifier: Operating System :: OS Independent
Requires-Python: >=3.9
License-File: LICENSE
Requires-Dist: sqlalchemy>1.4
Requires-Dist: xmlschema>=3.3.2
Requires-Dist: lxml>=5.1.0
Provides-Extra: docs
Requires-Dist: mkdocs-material>=9.5.34; extra == "docs"
Requires-Dist: mkdocstrings-python>=1.11.1; extra == "docs"
Provides-Extra: tests
Requires-Dist: pytest>=7.0; extra == "tests"
Dynamic: license-file
